rbpop/__init__.py
rbpop/utils.py
rbpop/win_manager.py
rbpop/win_pop.py
rbpop/prefab/__init__.py
rbpop/prefab/message.py
reft/__init__.py
reft/_mono_qshadows.py
reft/_mono_qsliders.py
reft/_rangef.py
reft/ft.py
reft/mono.py
reft/mono_ui.py
reft/test.py
reft-0.3.6.dist-info/METADATA
reft-0.3.6.dist-info/WHEEL
reft-0.3.6.dist-info/top_level.txt
reft-0.3.6.dist-info/RECORD
