Metadata-Version: 2.1
Name: reft
Version: 0.3.6
Summary: re format-tool (FT FDict Flist Fset...) and a simple mono-like control language (Support QMonoWidget QMonoInspector if PyQt5 is installed, but not neccessary if not used)
Author-email: 2229066748@qq.com
Maintainer: Eagle'sBaby
Maintainer-email: 2229066748@qq.com
License: Apache Licence 2.0
Keywords: re
Classifier: Programming Language :: Python :: 3
Classifier: Operating System :: Microsoft :: Windows
Requires-Python: >=3.10
